[
  {
    "id": "STR",
    "name": "STR",
    "normalMin": 4,
    "reliefMinPerBatch": 2,
    "priority": 1,
    "isMandatory": true,
    "backupTarget": 4,
    "description": "正班缺口：目前可上線人數低於正班最低人數。",
    "note": ""
  },
  {
    "id": "雷射",
    "name": "雷射",
    "normalMin": 3,
    "reliefMinPerBatch": 2,
    "priority": 4,
    "isMandatory": true,
    "backupTarget": 4,
    "description": "輪休單批最低人數：請填「單一批次」休息時，這個站點至少還要保留幾位已上線人員。",
    "note": ""
  },
  {
    "id": "ATB",
    "name": "ATB",
    "normalMin": 2,
    "reliefMinPerBatch": 2,
    "priority": 14,
    "isMandatory": true,
    "backupTarget": 4,
    "description": "系統會自動以 單批最低 × 2 作為兩批輪休的安全需求。",
    "note": ""
  },
  {
    "id": "LRT",
    "name": "LRT",
    "normalMin": 2,
    "reliefMinPerBatch": 2,
    "priority": 13,
    "isMandatory": true,
    "backupTarget": 4,
    "description": "排班優先序：去重分派時的預設保站順序，數字越小越優先。",
    "note": ""
  },
  {
    "id": "EL01",
    "name": "EL01",
    "normalMin": 2,
    "reliefMinPerBatch": 2,
    "priority": 2,
    "isMandatory": true,
    "backupTarget": 4,
    "description": "是否必站：Y 代表該站點需優先保住，不建議缺站。",
    "note": ""
  },
  {
    "id": "上料",
    "name": "上料",
    "normalMin": 2,
    "reliefMinPerBatch": 1,
    "priority": 7,
    "isMandatory": true,
    "backupTarget": 2,
    "description": "備援目標人數：建議至少要會此站的人數，預設為 MAX(正班最低, 輪休單批×2)。",
    "note": ""
  },
  {
    "id": "返修",
    "name": "返修",
    "normalMin": 3,
    "reliefMinPerBatch": 1,
    "priority": 5,
    "isMandatory": true,
    "backupTarget": 3,
    "description": "",
    "note": ""
  },
  {
    "id": "備料",
    "name": "備料",
    "normalMin": 1,
    "reliefMinPerBatch": 0,
    "priority": 17,
    "isMandatory": true,
    "backupTarget": 1,
    "description": "",
    "note": ""
  },
  {
    "id": "複判",
    "name": "複判",
    "normalMin": 0,
    "reliefMinPerBatch": 0,
    "priority": 19,
    "isMandatory": null,
    "backupTarget": 0,
    "description": "",
    "note": ""
  },
  {
    "id": "PKS",
    "name": "PKS",
    "normalMin": 2,
    "reliefMinPerBatch": 1,
    "priority": 9,
    "isMandatory": true,
    "backupTarget": 2,
    "description": "",
    "note": ""
  },
  {
    "id": "物料",
    "name": "物料",
    "normalMin": 1,
    "reliefMinPerBatch": 1,
    "priority": 8,
    "isMandatory": true,
    "backupTarget": 2,
    "description": "",
    "note": ""
  },
  {
    "id": "EL02",
    "name": "EL02",
    "normalMin": 1,
    "reliefMinPerBatch": 1,
    "priority": 10,
    "isMandatory": true,
    "backupTarget": 2,
    "description": "",
    "note": ""
  },
  {
    "id": "FRS",
    "name": "FRS",
    "normalMin": 2,
    "reliefMinPerBatch": 1,
    "priority": 3,
    "isMandatory": true,
    "backupTarget": 2,
    "description": "",
    "note": ""
  },
  {
    "id": "JBS",
    "name": "JBS",
    "normalMin": 2,
    "reliefMinPerBatch": 2,
    "priority": 16,
    "isMandatory": true,
    "backupTarget": 4,
    "description": "",
    "note": ""
  },
  {
    "id": "JBC",
    "name": "JBC",
    "normalMin": 2,
    "reliefMinPerBatch": 2,
    "priority": 11,
    "isMandatory": true,
    "backupTarget": 4,
    "description": "",
    "note": ""
  },
  {
    "id": "MFC",
    "name": "MFC",
    "normalMin": 2,
    "reliefMinPerBatch": 2,
    "priority": 12,
    "isMandatory": true,
    "backupTarget": 4,
    "description": "",
    "note": ""
  },
  {
    "id": "MBC",
    "name": "MBC",
    "normalMin": 2,
    "reliefMinPerBatch": 2,
    "priority": 15,
    "isMandatory": true,
    "backupTarget": 4,
    "description": "",
    "note": ""
  },
  {
    "id": "EL03",
    "name": "EL03",
    "normalMin": 2,
    "reliefMinPerBatch": 2,
    "priority": 6,
    "isMandatory": true,
    "backupTarget": 4,
    "description": "",
    "note": ""
  },
  {
    "id": "管制站",
    "name": "管制站",
    "normalMin": 1,
    "reliefMinPerBatch": 1,
    "priority": 18,
    "isMandatory": true,
    "backupTarget": 2,
    "description": "",
    "note": ""
  }
]